MainUpdater/__init__.py
MainUpdater/example.MainUpdater
MainUpdater/main.py
MainUpdater/script.py
mainupdater-0.0.5.dist-info/METADATA
mainupdater-0.0.5.dist-info/WHEEL
mainupdater-0.0.5.dist-info/entry_points.txt
mainupdater-0.0.5.dist-info/RECORD
