Metadata-Version: 2.1
Name: mainupdater
Version: 0.0.5
Summary: Простое обновление файлов по ссылке
Home-page: https://github.com/MainPlay-TG/MainUpdater.py
Author: MainPlay TG
Author-email: xbox.roman6666666666@gmail.com
Requires-Python: >=3.7,<4.0
Classifier: Programming Language :: Python :: 3
Classifier: Programming Language :: Python :: 3.7
Classifier: Programming Language :: Python :: 3.8
Classifier: Programming Language :: Python :: 3.9
Classifier: Programming Language :: Python :: 3.10
Classifier: Programming Language :: Python :: 3.11
Classifier: Programming Language :: Python :: 3.12
Requires-Dist: mainshortcuts
Requires-Dist: requests
Project-URL: Repository, https://github.com/MainPlay-TG/MainUpdater.py
